{"GlobalPropertiesHash":"FGyqAQoVk9Q0OwRjLbNnX9QydCDrbqKhd0gg2rDlqqI=","FingerprintPatternsHash":"gq3WsqcKBUGTSNle7RKKyXRIwh7M8ccEqOqYvIzoM04=","PropertyOverridesHash":"8ZRc1sGeVrPBx4lD717BgRaQekyh78QKV9SKsdt638U=","InputHashes":["8Rc7ZKnTntE0Oa\u002BGuI5Qm8oQa4omXpRx9GpknpAsvJo=","IK\u002BMCPrr7wXtLHYehD8L8tyJHVNa/VZuu0Bxbq1vPag=","litfK9u8SjfeGp0Hu42hnKHpGKNKPmbyr66bIXFcKCw=","WT5ewTGtfuGJm1SegLrEQemEpErF/sB6LCwppc28CIA="],"CachedAssets":{"8Rc7ZKnTntE0Oa\u002BGuI5Qm8oQa4omXpRx9GpknpAsvJo=":{"Identity":"C:\\Users\\Pc\\source\\repos\\rguarnieri1\\Conta-Calorie\\Conta calorie\\Conta calorie\\Conta calorie.Client\\wwwroot\\appsettings.Development.json","SourceId":"Conta_calorie.Client","SourceType":"Discovered","ContentRoot":"C:\\Users\\Pc\\source\\repos\\rguarnieri1\\Conta-Calorie\\Conta calorie\\Conta calorie\\Conta calorie.Client\\wwwroot\\","BasePath":"/","RelativePath":"appsettings.Development#[.{fingerprint}]?.json","AssetKind":"All","AssetMode":"All","AssetRole":"Primary","AssetMergeBehavior":null,"AssetMergeSource":"","RelatedAsset":null,"AssetTraitName":null,"AssetTraitValue":null,"Fingerprint":"tswichycbp","Integrity":"c/lfngzrIF/BxNxQwHaX/Pop1wh4aMKu8dUEyzjHcew=","CopyToOutputDirectory":"Never","CopyToPublishDirectory":"PreserveNewest","OriginalItemSpec":"wwwroot\\appsettings.Development.json","FileLength":127,"LastWriteTime":"2026-06-09T07:19:06.7969893+00:00"},"IK\u002BMCPrr7wXtLHYehD8L8tyJHVNa/VZuu0Bxbq1vPag=":{"Identity":"C:\\Users\\Pc\\source\\repos\\rguarnieri1\\Conta-Calorie\\Conta calorie\\Conta calorie\\Conta calorie.Client\\wwwroot\\appsettings.json","SourceId":"Conta_calorie.Client","SourceType":"Discovered","ContentRoot":"C:\\Users\\Pc\\source\\repos\\rguarnieri1\\Conta-Calorie\\Conta calorie\\Conta calorie\\Conta calorie.Client\\wwwroot\\","BasePath":"/","RelativePath":"appsettings#[.{fingerprint}]?.json","AssetKind":"All","AssetMode":"All","AssetRole":"Primary","AssetMergeBehavior":null,"AssetMergeSource":"","RelatedAsset":null,"AssetTraitName":null,"AssetTraitValue":null,"Fingerprint":"tswichycbp","Integrity":"c/lfngzrIF/BxNxQwHaX/Pop1wh4aMKu8dUEyzjHcew=","CopyToOutputDirectory":"Never","CopyToPublishDirectory":"PreserveNewest","OriginalItemSpec":"wwwroot\\appsettings.json","FileLength":127,"LastWriteTime":"2026-06-09T07:19:06.7979863+00:00"}},"CachedCopyCandidates":{}}